cpld_img_tools/__init__.py
cpld_img_tools/cpld2hpm.py
cpld_img_tools/jed_conv.py
cpld_img_tools-0.2.1.dist-info/METADATA
cpld_img_tools-0.2.1.dist-info/WHEEL
cpld_img_tools-0.2.1.dist-info/entry_points.txt
cpld_img_tools-0.2.1.dist-info/top_level.txt
cpld_img_tools-0.2.1.dist-info/RECORD
