Metadata-Version: 2.1
Name: cpld-img-tools
Version: 0.2.1
Summary: CPLD image tools
Home-page: https://techlab.desy.de
Author: Patrick Huesmann
Author-email: patrick.huesmann@desy.de
License: BSD
Keywords: mmc cpld jedec
Platform: UNKNOWN
Classifier: Programming Language :: Python :: 3.6
Classifier: Operating System :: OS Independent
Classifier: Environment :: Console
Classifier: License :: OSI Approved :: BSD License
Classifier: Intended Audience :: Developers
Classifier: Development Status :: 3 - Alpha
Requires-Python: >=3.6
Requires-Dist: bin2hpm (>=0.2.1)
